{
    "fluentMethods": true,
    "relationships": [
        {
            "relationshipType": "many-to-one",
            "relationshipName": "myGroup",
            "otherEntityName": "myGroup",
            "otherEntityField": "id"
        },
        {
            "relationshipType": "many-to-one",
            "relationshipName": "electoralDistrict",
            "otherEntityName": "electoralDistrict",
            "otherEntityField": "id"
        },
        {
            "relationshipType": "many-to-one",
            "relationshipName": "municipality",
            "otherEntityName": "municipality",
            "otherEntityField": "id"
        }
    ],
    "fields": [
        {
            "fieldName": "username",
            "fieldType": "String",
            "fieldValidateRules": [
                "required"
            ]
        },
        {
            "fieldName": "name",
            "fieldType": "String",
            "fieldValidateRules": [
                "required"
            ]
        },
        {
            "fieldName": "surname",
            "fieldType": "String",
            "fieldValidateRules": [
                "required"
            ]
        },
        {
            "fieldName": "documentType",
            "fieldType": "String",
            "fieldValidateRules": [
                "required"
            ]
        },
        {
            "fieldName": "documentNr",
            "fieldType": "String",
            "fieldValidateRules": [
                "required"
            ]
        },
        {
            "fieldName": "email",
            "fieldType": "String",
            "fieldValidateRules": [
                "required",
                "pattern"
            ],
            "fieldValidateRulesPattern": "^[^@\\s]+@[^@\\s]+\\.[^@\\s]+$"
        },
        {
            "fieldName": "birthdate",
            "fieldType": "LocalDate",
            "fieldValidateRules": [
                "required"
            ]
        },
        {
            "fieldName": "pesel",
            "fieldType": "String",
            "fieldValidateRules": [
                "required",
                "minlength",
                "maxlength"
            ],
            "fieldValidateRulesMinlength": 11,
            "fieldValidateRulesMaxlength": 11
        }
    ],
    "changelogDate": "20180403173350",
    "entityTableName": "my_user",
    "dto": "no",
    "pagination": "no",
    "service": "no",
    "jpaMetamodelFiltering": false,
    "microserviceName": "msapp"
}